curve_fit/__init__.py
curve_fit/annealing.py
curve_fit.annealing-0.0.3.dist-info/LICENSE
curve_fit.annealing-0.0.3.dist-info/METADATA
curve_fit.annealing-0.0.3.dist-info/WHEEL
curve_fit.annealing-0.0.3.dist-info/top_level.txt
curve_fit.annealing-0.0.3.dist-info/RECORD
