Metadata-Version: 2.1
Name: curve-fit.annealing
Version: 0.0.3
Summary: Curve fitting with global optimization routines
Home-page: https://github.com/amba/curve_fit.annealing
Author: Simon Reinhardt
Author-email: simon.reinhardt@physik.uni-regensburg.de
License: UNKNOWN
Keywords: curve fitting global optimization simulated annealing
Platform: UNKNOWN
Classifier: Programming Language :: Python :: 3
Classifier: License :: OSI Approved :: MIT License
Classifier: Operating System :: OS Independent
Requires-Python: >=3.5
Requires-Dist: scipy (>=1.2.0)
